LICENSE
README.rst
setup.py
XZGUtil/DBHelper.py
XZGUtil/ImagePositioning.py
XZGUtil/SYCMCryptUtil.py
XZGUtil/__init__.py
XZGUtil/dealFile.py
XZGUtil/downFile.py
XZGUtil/dyXB.py
XZGUtil/encAndDec.py
XZGUtil/fileEncryptionDecryption.py
XZGUtil/logger.py
XZGUtil/messageUtil.py
XZGUtil/pyqt5Logger.py
XZGUtil/quickTooling.py
XZGUtil/raspberryScan.py
XZGUtil/re_xzg.py
XZGUtil/screenShot.py
XZGUtil/timeUtil.py
XZGUtil/timer.py
XZGUtil/updateSpider.py
XZGUtil.egg-info/PKG-INFO
XZGUtil.egg-info/SOURCES.txt
XZGUtil.egg-info/dependency_links.txt
XZGUtil.egg-info/requires.txt
XZGUtil.egg-info/top_level.txt
xzgutil.egg-info/PKG-INFO
xzgutil.egg-info/SOURCES.txt
xzgutil.egg-info/dependency_links.txt
xzgutil.egg-info/requires.txt
xzgutil.egg-info/top_level.txt